{
  "id": 991535,
  "game": "mkworld",
  "season": 1,
  "createdOn": "2025-10-09T03:00:42.1689464Z",
  "verifiedOn": "2025-10-09T03:08:08.7317393Z",
  "numTeams": 3,
  "numPlayers": 12,
  "format": "4v4",
  "url": "/TableImage/991535.png",
  "tier": "SQ",
  "teams": [
    {
      "rank": 1,
      "scores": [
        {
          "score": 103,
          "multiplier": 1,
          "prevMmr": 5900,
          "newMmr": 6064,
          "delta": 164,
          "playerId": 13978,
          "playerName": "Moon Geonwoo",
          "playerDiscordId": "1308910449034788959",
          "playerCountryCode": "MX"
        },
        {
          "score": 72,
          "multiplier": 1,
          "prevMmr": 3709,
          "newMmr": 3873,
          "delta": 164,
          "playerId": 14604,
          "playerName": "revoltz3",
          "playerDiscordId": "562512850942427136",
          "playerCountryCode": "CL"
        },
        {
          "score": 88,
          "multiplier": 1,
          "prevMmr": 6223,
          "newMmr": 6387,
          "delta": 164,
          "playerId": 48574,
          "playerName": "Keinster",
          "playerDiscordId": "334438046642601986",
          "playerCountryCode": "MX"
        },
        {
          "score": 113,
          "multiplier": 1,
          "prevMmr": 5402,
          "newMmr": 5566,
          "delta": 164,
          "playerId": 48678,
          "playerName": "Larry66",
          "playerDiscordId": "691365636651221023",
          "playerCountryCode": "CL"
        }
      ]
    },
    {
      "rank": 2,
      "scores": [
        {
          "score": 65,
          "multiplier": 1,
          "prevMmr": 5292,
          "newMmr": 5292,
          "delta": 0,
          "playerId": 68239,
          "playerName": "Joltkip",
          "playerDiscordId": "256925159187808256",
          "playerCountryCode": "CA"
        },
        {
          "score": 93,
          "multiplier": 1,
          "prevMmr": 5735,
          "newMmr": 5735,
          "delta": 0,
          "playerId": 68515,
          "playerName": "Nolan",
          "playerDiscordId": "932819306578845767",
          "playerCountryCode": "US"
        },
        {
          "score": 93,
          "multiplier": 1,
          "prevMmr": 5413,
          "newMmr": 5413,
          "delta": 0,
          "playerId": 71444,
          "playerName": "SoberKart",
          "playerDiscordId": "401239472228007936",
          "playerCountryCode": "US"
        },
        {
          "score": 77,
          "multiplier": 1,
          "prevMmr": 4978,
          "newMmr": 4978,
          "delta": 0,
          "playerId": 71877,
          "playerName": "CHRIS2PHER",
          "playerDiscordId": "497908272657989654",
          "playerCountryCode": "US"
        }
      ]
    },
    {
      "rank": 3,
      "scores": [
        {
          "score": 86,
          "multiplier": 1,
          "prevMmr": 6129,
          "newMmr": 5965,
          "delta": -164,
          "playerId": 67764,
          "playerName": "Imp1904",
          "playerDiscordId": "597931655784562707",
          "playerCountryCode": "US"
        },
        {
          "score": 101,
          "multiplier": 1,
          "prevMmr": 6528,
          "newMmr": 6364,
          "delta": -164,
          "playerId": 73352,
          "playerName": "Ace.",
          "playerDiscordId": "565628872503066624",
          "playerCountryCode": "US"
        },
        {
          "score": 56,
          "multiplier": 1,
          "prevMmr": 4314,
          "newMmr": 4150,
          "delta": -164,
          "playerId": 74731,
          "playerName": "Loscomical",
          "playerDiscordId": "1085390833072746558",
          "playerCountryCode": "CA"
        },
        {
          "score": 37,
          "multiplier": 1,
          "prevMmr": 4665,
          "newMmr": 4501,
          "delta": -164,
          "playerId": 74863,
          "playerName": "Shortrat",
          "playerDiscordId": "1395498941675602030",
          "playerCountryCode": "CA"
        }
      ]
    }
  ],
  "tableMessageId": "1425679345891938305",
  "updateMessageId": "1425681222683852822",
  "authorId": "1308910449034788959"
}